<?xml version="1.0" encoding="utf-8" ?>
<elements>
	<info>
		<update version="0.0.4">
			<file name="sources.xml" url="https://raw.githubusercontent.com/SVDev-768/aurorabuilderSapperClass/main/user/source.xml" />
		</update>
	</info>
	<element name="Sapper Homebrew" type="Source" source="Homebrew" id="ID_WOTC_SOURCE_SAPPER_HOMEBREW">
		<description>
			<p><strong>A homebrew class created on Tumblr to create a unique spellcaster among the world of D&amp;D.</strong></p>
        </description>
		<setters>
			<set name="abbreviation">SHB</set>
            <set name="url">https://www.tumblr.com/brewskis-dnd-homebrewery/175262046268/sapper</set>
            <set name="image">https://raw.githubusercontent.com/SVDev-768/aurorabuilderSapperClass/main/aurora-sapper-homebrew/Sapper-Icon.png</set>
            <set name="author" abbreviation="WOTC" url="http://dnd.wizards.com">Wizards of the Coast</set>
            <set name="official">false</set>
			<set name="supplement">false</set>
			<set name="playtest">false</set>
			<set name="third-party">false</set>
			<set name="homebrew">true</set>
			<set name="league">false</set>
            <set name="release">20180625</set>
		</setters>
	</element>
</elements>